{
  "nodes":[
                { "name": "Emotion", "x":500, "y":400, "fixed":"true"},
                { "name": "Amusement"},
                { "name": "Angry" },
                { "name": "Compassion" },
                { "name": "Contempt" },
                { "name": "Disappointment" },
                { "name": "Admiration" },
                { "name": "Disgust" },
                { "name": "Fear" },
                { "name": "Guilt" },
                { "name": "Hate" },
                { "name": "Interest" },
                { "name": "Joy" },
                { "name": "Love" },
                { "name": "Pride" },
                { "name": "Regret" },
                { "name": "Relief" },
                { "name": "Sadness" },
                { "name": "Pleasure" },
                { "name": "Shame" },
                { "name": "Shame" }
  ],
  "links":[
                { "source": 0, "target":1,"value":10},
                { "source": 0, "target":2,"value":200},
                { "source": 0, "target":3,"value":200},
                { "source": 0, "target":4,"value":200},
                { "source": 0, "target":5,"value":200},
                { "source": 0, "target":6,"value":200},
                { "source": 0, "target":7,"value":300},
                { "source": 0, "target":8,"value":100},
                { "source": 0, "target":9,"value":300},
                { "source": 0, "target":10,"value":300},
                { "source": 0, "target":11,"value":300},
                { "source": 0, "target":12,"value":200},
                { "source": 0, "target":13,"value":200},
                { "source": 0, "target":14,"value":200},
                { "source": 0, "target":15,"value":200},
                { "source": 0, "target":16,"value":200},
                { "source": 0, "target":17,"value":200},
                { "source": 0, "target":18,"value":200}
                { "source": 0, "target":19,"value":200}
  ]
}